hep_rest_api/__init__.py
hep_rest_api/api_client.py
hep_rest_api/configuration.py
hep_rest_api/entry.py
hep_rest_api/rest.py
hep_rest_api/utils.py
hep_rest_api/api/__init__.py
hep_rest_api/api/rest_api.py
hep_rest_api/models/__init__.py
hep_rest_api/models/auth_cache_request.py
hep_rest_api/models/auth_cache_response.py
hep_rest_api/models/cancel_proof_request.py
hep_rest_api/models/cancel_proof_response.py
hep_rest_api/models/create_auth_cache_response.py
hep_rest_api/models/create_pay_cache_response.py
hep_rest_api/models/create_proof_request.py
hep_rest_api/models/create_proof_response.py
hep_rest_api/models/dapp.py
hep_rest_api/models/newchain_transaction_response.py
hep_rest_api/models/newforce_daily_stats_response.py
hep_rest_api/models/newid_response.py
hep_rest_api/models/order.py
hep_rest_api/models/order_item.py
hep_rest_api/models/pay_cache_request.py
hep_rest_api/models/pay_cache_response.py
hep_rest_api/models/proof.py
hep_rest_api/models/proof_data.py
hep_rest_api/models/proof_response.py
hep_rest_api/models/proof_reward.py
hep_rest_api/models/receipt_field.py
hep_rest_api/models/retrieve_dapp_daily_stats_response.py
hep_rest_api/models/retrieve_oracle_response.py
hep_rest_api/models/retrieve_proof_receipts_request.py
hep_rest_api/models/retrieve_proof_receipts_response.py
hep_rest_api/models/retrieve_proof_rewards_request.py
hep_rest_api/models/retrieve_proof_rewards_response.py
hep_rest_api/models/thing.py
hep_rest_api/scenarios/__init__.py
hep_rest_api/scenarios/auth.py
hep_rest_api/scenarios/pay.py
hep_rest_api/scenarios/proof.py
test/__init__.py
test/test_auth_cache_request.py
test/test_auth_cache_response.py
test/test_basic.py
test/test_cancel_proof_request.py
test/test_cancel_proof_response.py
test/test_create_auth_cache_response.py
test/test_create_pay_cache_response.py
test/test_create_proof_request.py
test/test_create_proof_response.py
test/test_dapp.py
test/test_newchain_transaction_response.py
test/test_newforce_daily_stats_response.py
hep_rest_api-1.0.12.dist-info/METADATA
hep_rest_api-1.0.12.dist-info/WHEEL
hep_rest_api-1.0.12.dist-info/top_level.txt
hep_rest_api-1.0.12.dist-info/RECORD
