Metadata-Version: 2.1
Name: hep-rest-api
Version: 1.0.12
Summary: HEP REST API
Home-page: http://github.com/newtonproject/hep-sdk
Author: UNKNOWN
Author-email: weixuefeng@lubangame.com
License: UNKNOWN
Keywords: newtonproject.org,Hyper Exchange Protocol,HEP REST API
Platform: UNKNOWN
Requires-Dist: urllib3 (>=1.15)
Requires-Dist: six (>=1.10)
Requires-Dist: certifi
Requires-Dist: python-dateutil
Requires-Dist: fastecdsa (==1.7.3)
Requires-Dist: pysha3 (==1.0.2)
Requires-Dist: base58 (==1.0.3)
